mailauth/__init__.py
mailauth/_version.py
mailauth/backends.py
mailauth/forms.py
mailauth/signing.py
mailauth/urls.py
mailauth/views.py
mailauth/contrib/__init__.py
mailauth/contrib/admin/__init__.py
mailauth/contrib/admin/admin.py
mailauth/contrib/admin/apps.py
mailauth/contrib/admin/views.py
mailauth/contrib/admin/locale/de/LC_MESSAGES/django.mo
mailauth/contrib/admin/locale/de/LC_MESSAGES/django.po
mailauth/contrib/admin/static/mailauth_admin/css/login.css
mailauth/contrib/admin/templates/mailauth_admin/login.html
mailauth/contrib/admin/templates/registration/login_requested.html
mailauth/contrib/user/__init__.py
mailauth/contrib/user/admin.py
mailauth/contrib/user/apps.py
mailauth/contrib/user/models.py
mailauth/contrib/user/signals.py
mailauth/contrib/user/locale/de/LC_MESSAGES/django.mo
mailauth/contrib/user/locale/de/LC_MESSAGES/django.po
mailauth/contrib/user/migrations/0001_initial.py
mailauth/contrib/user/migrations/0002_emailuser_session_salt.py
mailauth/contrib/user/migrations/0003_ci_unique_index.py
mailauth/contrib/user/migrations/0004_auto_20200812_0722.py
mailauth/contrib/user/migrations/0005_emailuser_email_hash_alter_emailuser_email.py
mailauth/contrib/user/migrations/__init__.py
mailauth/contrib/wagtail/__init__.py
mailauth/contrib/wagtail/apps.py
mailauth/contrib/wagtail/urls.py
mailauth/contrib/wagtail/views.py
mailauth/contrib/wagtail/templates/wagtailadmin/login.html
mailauth/templates/registration/login_email.txt
mailauth/templates/registration/login_subject.txt
django_mail_auth-3.5.5.dist-info/licenses/LICENSE
django_mail_auth-3.5.5.dist-info/WHEEL
django_mail_auth-3.5.5.dist-info/METADATA
django_mail_auth-3.5.5.dist-info/RECORD
