Metadata-Version: 2.4
Name: django-mail-auth
Version: 3.5.5
Summary: Django authentication via login URLs, no passwords required.
Keywords: django,otp,email,authentication,passwordless
Author-email: Johannes Maron <johannes@maron.family>
Requires-Python: >=3.10
Classifier: Development Status :: 5 - Production/Stable
Classifier: Environment :: Console
Classifier: Intended Audience :: Developers
Classifier: License :: OSI Approved :: MIT License
Classifier: Operating System :: OS Independent
Classifier: Programming Language :: Python :: 3
Classifier: Programming Language :: Python :: 3.10
Classifier: Programming Language :: Python :: 3.11
Classifier: Programming Language :: Python :: 3.12
Classifier: Programming Language :: Python :: 3.13
Classifier: Programming Language :: Python :: 3.14
Classifier: Programming Language :: Python :: 3 :: Only
Classifier: Framework :: Django
Classifier: Framework :: Django :: 4.2
Classifier: Framework :: Django :: 5.2
Classifier: Framework :: Django :: 6.0
Classifier: Framework :: Wagtail
Classifier: Framework :: Wagtail :: 6
Classifier: Framework :: Wagtail :: 7
Classifier: Topic :: Internet
Classifier: Topic :: Internet :: WWW/HTTP
Classifier: Topic :: Software Development :: Quality Assurance
Classifier: Topic :: Software Development :: Testing
License-File: LICENSE
Requires-Dist: django>=4.2
Requires-Dist: django-citext ; extra == "postgres"
Requires-Dist: psycopg ; extra == "postgres"
Requires-Dist: wagtail>=6.3 ; extra == "wagtail"
Project-URL: Changelog, https://github.com/codingjoe/django-mail-auth/releases
Project-URL: Documentation, https://django-mail-auth.rtfd.io/
Project-URL: Funding, https://github.com/sponsors/codingjoe
Project-URL: Homepage, https://github.com/codingjoe/django-mail-auth
Project-URL: Issues, https://github.com/codingjoe/django-mail-auth/issues
Project-URL: Releasenotes, https://github.com/codingjoe/django-mail-auth/releases/latest
Project-URL: Source, https://github.com/codingjoe/django-mail-auth
Provides-Extra: postgres
Provides-Extra: wagtail
